setup.py
sd_distributions/Binomialdistribution.py
sd_distributions/Gaussiandistribution.py
sd_distributions/Generaldistribution.py
sd_distributions/__init__.py
sd_distributions.egg-info/PKG-INFO
sd_distributions.egg-info/SOURCES.txt
sd_distributions.egg-info/dependency_links.txt
sd_distributions.egg-info/not-zip-safe
sd_distributions.egg-info/top_level.txt